nonebot_plugin_nailongmagic-1.0.5.post2.dist-info/METADATA
nonebot_plugin_nailongmagic-1.0.5.post2.dist-info/WHEEL
nonebot_plugin_nailongmagic-1.0.5.post2.dist-info/entry_points.txt
nonebot_plugin_nailongmagic-1.0.5.post2.dist-info/licenses/LICENSE
nonebot_plugin_nailongmagic/__init__.py
nonebot_plugin_nailongmagic/config.py
nonebot_plugin_nailongmagic/handler.py
nonebot_plugin_nailongmagic/image_url.py
nonebot_plugin_nailongmagic/model/__init__.py
nonebot_plugin_nailongmagic/model/hf_model.py
nonebot_plugin_nailongmagic-1.0.5.post2.dist-info/RECORD
