Metadata-Version: 2.1
Name: nonebot-plugin-nailongmagic
Version: 1.0.5.post2
Summary: 通过指令将目标图片变成奶龙
Keywords: nonebot,plugin,image
Author-Email: 445 <2877834692@qq.com>
License: MIT
Project-URL: homepage, https://github.com/superbot-ai445/nonebot-plugin-nailongmagic
Project-URL: repository, https://github.com/superbot-ai445/nonebot-plugin-nailongmagic
Requires-Python: <4.0,>=3.9
Requires-Dist: nonebot2>=2.2.0
Requires-Dist: nonebot-plugin-alconna>=0.53.1
Requires-Dist: nonebot-plugin-uninfo>=0.5.0
Requires-Dist: pillow>=9
Requires-Dist: cookit[pydantic]>=0.8.1
Requires-Dist: huggingface-hub>=0.26.2
Requires-Dist: torch>=2.4
Requires-Dist: torchvision>=0.19
Requires-Dist: diffusers>=0.31.0
Requires-Dist: transformers>=4.47.0
Requires-Dist: accelerate>=1.2.0
Requires-Dist: peft>=0.14.0
